ni_measurement_generator/__main__.py
ni_measurement_generator/template.py
ni_measurement_generator/templates/measurement.measproj.mako
ni_measurement_generator/templates/measurement.measui.mako
ni_measurement_generator/templates/measurement.py.mako
ni_measurement_generator/templates/measurement.serviceconfig.mako
ni_measurement_generator/templates/start.bat.mako
ni_measurement_generator-0.11.1.dist-info/entry_points.txt
ni_measurement_generator-0.11.1.dist-info/WHEEL
ni_measurement_generator-0.11.1.dist-info/METADATA
ni_measurement_generator-0.11.1.dist-info/RECORD
