Metadata-Version: 2.1
Name: ni-measurement-generator
Version: 0.11.1
Summary: MeasurementLink Code Generator for Python
Author: NI
Author-email: opensource@ni.com
Requires-Python: >=3.8,<4.0
Classifier: Programming Language :: Python :: 3
Classifier: Programming Language :: Python :: 3.8
Classifier: Programming Language :: Python :: 3.9
Classifier: Programming Language :: Python :: 3.10
Classifier: Programming Language :: Python :: 3.11
Requires-Dist: Mako (>=1.2.1,<2.0.0)
Requires-Dist: click (>=8.1.3,<9.0.0)
